vsh_tools/basis.py
vsh_tools/bootstrap.py
vsh_tools/diagnostics.py
vsh_tools/fit.py
vsh_tools/glide.py
vsh_tools/legacy.py
vsh_tools/linalg.py
vsh_tools/metrics.py
vsh_tools/outliers.py
vsh_tools/power.py
vsh_tools/rgq.py
vsh_tools/scalar_basis.py
vsh_tools/significance.py
vsh_tools/stats.py
vsh_tools/transforms.py
vsh_tools/deprecated/__init__.py
vsh_tools/deprecated/auto_elim.py
vsh_tools/deprecated/bootstrap_sample.py
vsh_tools/deprecated/generate_test_data.py
vsh_tools/deprecated/glide_func.py
vsh_tools/deprecated/implementation_comparison.py
vsh_tools/deprecated/matrix_calc.py
vsh_tools/deprecated/pmt_convert.py
vsh_tools/deprecated/rgq_func.py
vsh_tools/deprecated/ssh_expansion.py
vsh_tools/deprecated/stats_func.py
vsh_tools/deprecated/test.py
vsh_tools/deprecated/tune_para.py
vsh_tools/deprecated/vec_sph_harm.py
vsh_tools/deprecated/verify_code.py
vsh_tools/deprecated/vsh_aux_info.py
vsh_tools/deprecated/vsh_expansion.py
vsh_tools/deprecated/vsh_expension.py
vsh_tools/deprecated/vsh_fit.py
vsh_tools/deprecated/vsh_power.py
vsh_tools/deprecated/vsh_significance.py
vsh_tools/deprecated/vsh_stat.py
vsh_tools/deprecated/vsh_stats.py
vsh_tools-0.1.0.dist-info/licenses/LICENSE
vsh_tools-0.1.0.dist-info/METADATA
vsh_tools-0.1.0.dist-info/WHEEL
vsh_tools-0.1.0.dist-info/top_level.txt
vsh_tools-0.1.0.dist-info/RECORD
