Metadata-Version: 2.4
Name: vsh-tools
Version: 0.1.0
Summary: Vector Spherical Harmonics analysis tools (rotation, glide, quadrupole)
Author-email: Neo <niu.liu@nju.edu.cn>
License: MIT
Project-URL: Homepage, https://git.nju.edu.cn/neo/vsh
Requires-Python: >=3.9
License-File: LICENSE
Requires-Dist: numpy>=1.22
Requires-Dist: scipy>=1.9
Requires-Dist: astropy>=5.0
Requires-Dist: matplotlib>=3.7
Provides-Extra: dev
Requires-Dist: pytest>=7.4; extra == "dev"
Dynamic: license-file
